{
  "_id": "kw013",
  "name": "Cerastus Shock Lance",
  "type": "vehiclecomponent",
  "img": "icons/svg/item-bag.svg",
  "system": {
    "componentType": "Main / Cerastus Lancer",
    "facing": "Front/Swivel",
    "power": 0,
    "space": 0,
    "damage": "3d10+8 E",
    "penetration": 10,
    "rof": "S/3/6",
    "clip": "\u2014",
    "range": 60,
    "qualities": "Shocking \u2014 also usable as melee: 3d10+30 E Pen 20, Power Field, Shocking, Felling[10], Destroyer[3]",
    "status": "ok",
    "description": "The Lancer's signature weapon \u2014 a crackling energy lance usable at range or in close combat."
  }
}